skrate/__init__.py
skrate/game_logic.py
skrate/models.py
skrate/rates_by_trick.sql
skrate/server.py
skrate/tricks.py
skrate/static/favicon.ico
skrate/static/skrate.css
skrate/static/skrate.js
skrate/templates/game.html
skrate/templates/index.html
skrate/templates/trick.html
skrate/templates/trickstats.html
skrate-0.2.data/scripts/run_skrate
skrate-0.2.dist-info/LICENSE.txt
skrate-0.2.dist-info/METADATA
skrate-0.2.dist-info/WHEEL
skrate-0.2.dist-info/top_level.txt
skrate-0.2.dist-info/RECORD
