Metadata-Version: 2.1
Name: skrate
Version: 0.2
Summary: App for skateboarding progression analysis
Home-page: https://github.com/lenknerd/skrate
Author: David Lenkner
License: MIT
Platform: UNKNOWN
Classifier: Programming Language :: Python :: 3
Classifier: License :: OSI Approved :: MIT License
Classifier: Operating System :: OS Independent
Requires-Dist: click (>=7.0)
Requires-Dist: Flask (>=1.1.1)
Requires-Dist: Flask-Ext (>=0.1)
Requires-Dist: Flask-Session (>=0.3.1)
Requires-Dist: Flask-SQLAlchemy (>=2.4.1)
Requires-Dist: Flask-Testing (>=0.7.1)
Requires-Dist: psycopg2-binary (>=2.8.4)
Requires-Dist: pytest (>=5.3.2)
Requires-Dist: SQLAlchemy (>=1.3.12)
